{
    "start_up": {
        "action": "StartApp",
        "package": "com.tencent.KiHan",
        "next": [
            "start_naruto"
        ],
        "focus": "[color:DeepSkyBlue]火影忍者，启动！[/color]"
    },
    "start_naruto": {
        "next": [
            "check_main_screen_and_stop",
            "before_game",
            "[JumpBack]splash_screen",
            "[JumpBack]start_up_loading",
            "[JumpBack]close_before_game_notice",
            "[JumpBack]close_teenager_page"
        ],
        "on_error": [
            "start_up"
        ],
        "timeout": 30000
    },
    "restart_naruto": {
        "action": "StopApp",
        "package": "com.tencent.KiHan",
        "next": [
            "start_up"
        ],
        "focus": "[color:tomato]重启火影[/color]"
    },
    "splash_screen": {
        "recognition": "OCR",
        "expected": [
            "腾讯游戏",
            "魔方工作室",
            "BANDAI"
        ],
        "focus": "[color:DeepSkyBlue]商标页面[/color]"
    },
    "start_up_loading": {
        "recognition": "OCR",
        "expected": [
            "%"
        ],
        "roi": [
            558,
            503,
            162,
            113
        ],
        "focus": "[color:DeepSkyBlue]游戏加载中...[/color]"
    },
    "before_game": {
        "recognition": "TemplateMatch",
        "template": "Startup/naruto_logo.png",
        "threshold": 0.4,
        "roi": [
            6,
            0,
            348,
            218
        ],
        "next": [
            "click_start_game",
            "[JumpBack]start_up_loading",
            "[JumpBack]close_teenager_page",
            "[JumpBack]agree_log_in",
            "[JumpBack]agree_info"
        ],
        "on_error": [
            "start_up"
        ],
        "timeout": 15000
    },
    "close_teenager_page": {
        "recognition": "TemplateMatch",
        "template": "Startup/teenager_page.png",
        "roi": [
            1080,
            0,
            93,
            50
        ],
        "action": "Click",
        "pre_wait_freezes": 500,
        "focus": "[color:DeepSkyBlue]尝试关闭青少年界面[/color]"
    },
    "close_before_game_notice": {
        "recognition": "TemplateMatch",
        "template": "Startup/x.png",
        "roi": [
            1010,
            53,
            93,
            77
        ],
        "action": "Click",
        "post_delay": 500,
        "focus": "[color:DeepSkyBlue]关闭游戏前公告[/color]"
    },
    "agree_log_in": {
        "recognition": "OCR",
        "expected": "同意",
        "roi": [
            454,
            382,
            385,
            281
        ],
        "action": "Click",
        "post_delay": 500,
        "next": "empty_number",
        "timeout": 1000,
        "focus": "[color:DeepSkyBlue]确认登录[/color]"
    },
    "empty_number": {
        "recognition": "OCR",
        "expected": "位数不足",
        "action": "Custom",
        "custom_action": "StopTaskList",
        "focus": "[color:tomato]当前没有可登录的账号[/color]"
    },
    "agree_info": {
        "recognition": "OCR",
        "expected": "同意",
        "roi": [
            465,
            459,
            365,
            234
        ],
        "action": "Click",
        "post_delay": 1500,
        "focus": "[color:DeepSkyBlue]确认同意信息[/color]"
    },
    "click_start_game": {
        "recognition": "OCR",
        "expected": "开始游戏",
        "roi": [
            494,
            530,
            291,
            153
        ],
        "action": "Click",
        "next": [
            "before_game_loading"
        ],
        "on_error": [
            "back_main_screen_and_stop"
        ],
        "timeout": 5000,
        "focus": "[color:DeepSkyBlue]点击开始游戏[/color]"
    },
    "before_game_loading": {
        "recognition": "OCR",
        "expected": [
            "%"
        ],
        "roi": [
            558,
            503,
            162,
            113
        ],
        "next": [
            "without_before_game_loading"
        ],
        "focus": "[color:DeepSkyBlue]游戏加载中...[/color]"
    },
    "without_before_game_loading": {
        "recognition": "OCR",
        "expected": [
            "%",
            "资源加载"
        ],
        "roi": [
            558,
            503,
            162,
            113
        ],
        "inverse": true,
        "next": [
            "back_main_screen_and_stop"
        ],
        "focus": "[color:DeepSkyBlue]结束开始加载[/color]"
    }
}
